initable/__init__.py
initable/_vendor/__init__.py
initable/_vendor/funcutils.py
initable/initable.py
initable-0.2.1.dist-info/LICENSE
initable-0.2.1.dist-info/WHEEL
initable-0.2.1.dist-info/METADATA
initable-0.2.1.dist-info/RECORD
