Metadata-Version: 2.1
Name: initable
Version: 0.2.1
Summary: Initable is a Python package that helps create DRY-er classes.
Author: Payson Wallach
Author-email: paysonwallach@icloud.com
Requires-Python: >=3.6,<4.0
Classifier: Programming Language :: Python :: 3
Classifier: Programming Language :: Python :: 3.6
Classifier: Programming Language :: Python :: 3.7
Classifier: Programming Language :: Python :: 3.8
